LICENSE
MANIFEST.in
README.rst
setup.py
django_utools.egg-info/PKG-INFO
django_utools.egg-info/SOURCES.txt
django_utools.egg-info/dependency_links.txt
django_utools.egg-info/top_level.txt
utils/__init__.py
utils/backend.py
utils/generators.py
utils/tokens.py